{
  "/js/app/product/index.js": "/js/app/product/index.eb9aa19ed90807cabf25.js",
  "/js/app/account_settings/index.js": "/js/app/account_settings/index.ba0e5db5c1811fa337e0.js",
  "/js/app/report/index.js": "/js/app/report/index.a9b2188cf1ffe3be8d16.js",
  "/js/app/item_meta/index.js": "/js/app/item_meta/index.71f59e9fb8b9c6b60351.js",
  "/js/app/alert/index.js": "/js/app/alert/index.f81d6c3f302ee791942d.js",
  "/js/app/item/index.js": "/js/app/item/index.85e6cd8422ae5d245550.js",
  "/js/app/domain/index.js": "/js/app/domain/index.8e524529e38d20995098.js",
  "/js/app/url/index.js": "/js/app/url/index.31d70aefb7dcf6ec3d71.js",
  "/js/app/domain_meta/edit.js": "/js/app/domain_meta/edit.dbf98f72792a020ccf0a.js",
  "/js/app/user/index.js": "/js/app/user/index.6f1a3e5bf34558e79d3b.js",
  "/js/app/role/index.js": "/js/app/role/index.d29e6a9c7911e656f25d.js",
  "/js/app/permission/index.js": "/js/app/permission/index.7f484bae850cdee4db5d.js",
  "/js/app/group/index.js": "/js/app/group/index.a10ebd8ed73b7443c93a.js",
  "/js/app/admin/app_pref/index.js": "/js/app/admin/app_pref/index.271cc50b4920fc96a94c.js",
  "/js/app/admin/user_activity_log/index.js": "/js/app/admin/user_activity_log/index.3abd41eed9da031bdc9a.js",
  "/js/app/user/show.js": "/js/app/user/show.a3fbdc941755c0370846.js",
  "/js/app/user/edit.js": "/js/app/user/edit.6fd02e5cfd0f6f9a6ed3.js",
  "/js/app/user/create.js": "/js/app/user/create.b8b9d9b443db9e1d268b.js",
  "/js/app/role/show.js": "/js/app/role/show.2ba46adb4408fe910568.js",
  "/js/app/role/edit.js": "/js/app/role/edit.784bf9158a86d0a66f39.js",
  "/js/app/role/create.js": "/js/app/role/create.3277035c87080dcfbf9e.js",
  "/js/app/permission/show.js": "/js/app/permission/show.1f0242e5d63b1440f7a6.js",
  "/js/app/permission/edit.js": "/js/app/permission/edit.7e159932e8c400fc7be4.js",
  "/js/app/permission/create.js": "/js/app/permission/create.a9dcf23c0787c88825ed.js",
  "/js/app/group/show.js": "/js/app/group/show.a2c160703cf15d145c7b.js",
  "/js/app/group/edit.js": "/js/app/group/edit.278995bdc0ebbefe68ce.js",
  "/js/app/group/create.js": "/js/app/group/create.3e3a92da0aaba1ba762b.js",
  "/js/app/url/edit.js": "/js/app/url/edit.e9ea864bfbfb5bfc576f.js",
  "/js/app/url/create.js": "/js/app/url/create.1a18ed9417ac54e71847.js",
  "/js/app/domain/show.js": "/js/app/domain/show.fdffab3c23036becf4fb.js",
  "/js/app/domain/edit.js": "/js/app/domain/edit.900db9470f1cd18485f4.js",
  "/js/app/domain/create.js": "/js/app/domain/create.e97c012d97891776709e.js",
  "/js/auth/register.js": "/js/auth/register.e01a7a5d96a6f378f706.js",
  "/js/auth/login.js": "/js/auth/login.a99cc652f53197538ca4.js",
  "/js/auth/forgot.js": "/js/auth/forgot.5bea36696d9914de1110.js",
  "/js/app.js": "/js/app.6dcee1cc754137036892.js",
  "/css/app.css": "/css/app.f974982dc8b192292084.css",
  "/css/auth.css": "/css/auth.f974982dc8b192292084.css"
}